{
  "pages": [
    {
      "path": "pages/home/home"
    },
    {
      "path": "pages/backup/backup",
      "style": {
        "navigationBarTitleText": "Backup",
        "navigationBarTextStyle": "black",
        "navigationBarBackgroundColor": "#ffffff",
        "backgroundColor": "#f8f8f8"
      }
    },
    {
      "path": "pages/settings/settings",
      "style": {
        "navigationBarTitleText": "Settings",
        "navigationBarTextStyle": "black",
        "navigationBarBackgroundColor": "#ffffff",
        "backgroundColor": "#f8f8f8"
      }
    }
  ],
  
  "tabBar": {
    "color": "#999999",
    "selectedColor": "#007aff",
    "backgroundColor": "#ffffff",
    "borderStyle": "black",
    "list": [
      {
        "pagePath": "pages/home/home",
        "iconPath": "static/icons/home.png",
        "selectedIconPath": "static/icons/home-selected.png",
        "text": "Home"
      },
      {
        "pagePath": "pages/backup/backup",
        "iconPath": "static/icons/backup.png",
        "selectedIconPath": "static/icons/back-selected.png",
        "text": "Backup"
      },
      {
        "pagePath": "pages/settings/settings",
        "iconPath": "static/icons/settings.png",
        "selectedIconPath": "static/icons/setting-selected.png",
        "text": "Settings"
      }
    ]
  },
  "globalStyle": {
    "navigationBarTextStyle": "black",
    "navigationBarTitleText": "Auth",
    "navigationBarBackgroundColor": "#ffffff",
    "backgroundColor": "#f8f8f8"
  },
	"condition" : { //模式配置，仅开发期间生效
		"current": 0, //当前激活的模式(list 的索引项)
		"list": [
			{
				"name": "", //模式名称
				"path": "", //启动页面，必选
				"query": "" //启动参数，在页面的onLoad函数里面得到
			}
		]
	}
}
